LICENSE.md
README.md
setup.py
i2ls/__init__.py
visiology_py/__init__.py
visiology_py/authorization_token.py
visiology_py/base_api.py
visiology_py/connection.py
visiology_py/datacollection.py
visiology_py/decorators.py
visiology_py/viqube.py
visiology_py.egg-info/PKG-INFO
visiology_py.egg-info/SOURCES.txt
visiology_py.egg-info/dependency_links.txt
visiology_py.egg-info/requires.txt
visiology_py.egg-info/top_level.txt