Metadata-Version: 2.1
Name: visiology-py
Version: 0.10.3
Summary: High level wrappers for Visiology APIs: Smart Forms, ViQube and ViQube admin
Home-page: https://gitlab.com/polymedia-orv/orv/visiology-py
Author: Denis <codingjerk> Gruzdev
Author-email: codingjerk@gmail.com
License: MIT
Platform: UNKNOWN
License-File: LICENSE.md
